nfldb/__init__.py
nfldb/category.py
nfldb/db.py
nfldb/query.py
nfldb/sql.py
nfldb/team.py
nfldb/types.py
nfldb/update.py
nfldb/version.py
nfldb_redux-1.0.0a4.data/data/share/doc/nfldb/README.md
nfldb_redux-1.0.0a4.data/data/share/doc/nfldb/UNLICENSE
nfldb_redux-1.0.0a4.data/data/share/doc/nfldb/longdesc.rst
nfldb_redux-1.0.0a4.data/data/share/doc/nfldb/doc/category.html
nfldb_redux-1.0.0a4.data/data/share/doc/nfldb/doc/db.html
nfldb_redux-1.0.0a4.data/data/share/doc/nfldb/doc/index.html
nfldb_redux-1.0.0a4.data/data/share/doc/nfldb/doc/query.html
nfldb_redux-1.0.0a4.data/data/share/doc/nfldb/doc/sql.html
nfldb_redux-1.0.0a4.data/data/share/doc/nfldb/doc/team.html
nfldb_redux-1.0.0a4.data/data/share/doc/nfldb/doc/types.html
nfldb_redux-1.0.0a4.data/data/share/doc/nfldb/doc/update.html
nfldb_redux-1.0.0a4.data/data/share/doc/nfldb/doc/version.html
nfldb_redux-1.0.0a4.data/data/share/nfldb/config.ini.sample
nfldb_redux-1.0.0a4.data/scripts/nfldb-update
nfldb_redux-1.0.0a4.dist-info/COPYING
nfldb_redux-1.0.0a4.dist-info/METADATA
nfldb_redux-1.0.0a4.dist-info/WHEEL
nfldb_redux-1.0.0a4.dist-info/top_level.txt
nfldb_redux-1.0.0a4.dist-info/RECORD
