Metadata-Version: 2.1
Name: nfldb-redux
Version: 1.0.0a4
Summary: A library to manage and update NFL data in a relational database.
Home-page: https://github.com/derek-adair/nfldb
Author: Andrew Gallant
Author-email: nfldb@burntsushi.net
License: UNLICENSE
Platform: ANY
Classifier: License :: Public Domain
Classifier: Development Status :: 3 - Alpha
Classifier: Environment :: Console
Classifier: Intended Audience :: Developers
Classifier: Intended Audience :: End Users/Desktop
Classifier: Intended Audience :: Other Audience
Classifier: Operating System :: OS Independent
Classifier: Programming Language :: Python :: 3.5
Classifier: Programming Language :: Python :: 3.6
Classifier: Topic :: Database
Requires-Dist: nflgame-redux (>=2.0.2)
Requires-Dist: psycopg2
Requires-Dist: enum34
Requires-Dist: pytz
